gee_wetlands/__init__.py
gee_wetlands/common.py
gee_wetlands/gee_wetlands.py
gee_wetlands-0.0.1.dist-info/LICENSE
gee_wetlands-0.0.1.dist-info/METADATA
gee_wetlands-0.0.1.dist-info/WHEEL
gee_wetlands-0.0.1.dist-info/entry_points.txt
gee_wetlands-0.0.1.dist-info/top_level.txt
gee_wetlands-0.0.1.dist-info/RECORD
