Metadata-Version: 2.1
Name: gee_wetlands
Version: 0.0.1
Summary: Python Lib for doing wetland classifications in google earth engine
Author-email: Ryan Hamilton <ryan.hamilton@ec.gc.ca>
License: MIT License
Project-URL: Homepage, https://github.com/Hamilton97/gee_wetlands
Keywords: gee_wetlands
Classifier: Intended Audience :: Developers
Classifier: License :: OSI Approved :: MIT License
Classifier: Natural Language :: English
Classifier: Programming Language :: Python :: 3.8
Classifier: Programming Language :: Python :: 3.9
Classifier: Programming Language :: Python :: 3.10
Classifier: Programming Language :: Python :: 3.11
Classifier: Programming Language :: Python :: 3.12
Requires-Python: >=3.8
License-File: LICENSE
Requires-Dist: numpy
Provides-Extra: all
Requires-Dist: gee-wetlands[extra] ; extra == 'all'
Provides-Extra: extra
Requires-Dist: pandas ; extra == 'extra'
